tests/__init__.py
tests/async_test.py
tests/link_test.py
tests/misc_test.py
tests/pool_test.py
tests/sync_test.py
tests/test_links.py
ui/app.py
v2ray2proxy/__init__.py
v2ray2proxy/__main__.py
v2ray2proxy/base.py
v2ray2proxy-0.3.2.dist-info/licenses/LICENSE
v2ray2proxy-0.3.2.dist-info/METADATA
v2ray2proxy-0.3.2.dist-info/WHEEL
v2ray2proxy-0.3.2.dist-info/top_level.txt
v2ray2proxy-0.3.2.dist-info/RECORD
