Metadata-Version: 2.4
Name: v2ray2proxy
Version: 0.3.2
Summary: 🐍 Convert v2ray (vless://, vmess://, ss:// , trojan://) to local socks5:// & http:// proxies
Author-email: nichind <nichinddev@gmail.com>
License: MIT
Project-URL: Homepage, https://github.com/nichind/v2ray2proxy
Project-URL: Issues, https://github.com/nichind/v2ray2proxy/issues
Keywords: v2ray,v2core,v2ray-core,proxy,vless,vmess,shadowsocks,trojan,python,cli
Classifier: Programming Language :: Python :: 3.9
Classifier: License :: OSI Approved :: MIT License
Classifier: Operating System :: OS Independent
Requires-Python: >=3.9
License-File: LICENSE
Requires-Dist: psutil
Dynamic: license-file
